flask_smorest/__init__.py
flask_smorest/arguments.py
flask_smorest/blueprint.py
flask_smorest/error_handler.py
flask_smorest/etag.py
flask_smorest/exceptions.py
flask_smorest/fields.py
flask_smorest/globals.py
flask_smorest/pagination.py
flask_smorest/response.py
flask_smorest/utils.py
flask_smorest/spec/__init__.py
flask_smorest/spec/field_converters.py
flask_smorest/spec/plugins.py
flask_smorest/spec/templates/rapidoc.html
flask_smorest/spec/templates/redoc.html
flask_smorest/spec/templates/swagger_ui.html
flask_smorest-0.44.0.dist-info/AUTHORS.rst
flask_smorest-0.44.0.dist-info/LICENSE
flask_smorest-0.44.0.dist-info/METADATA
flask_smorest-0.44.0.dist-info/WHEEL
flask_smorest-0.44.0.dist-info/top_level.txt
flask_smorest-0.44.0.dist-info/RECORD
