Metadata-Version: 2.1
Name: flask-smorest
Version: 0.44.0
Summary: Flask/Marshmallow-based REST API framework
Home-page: https://github.com/marshmallow-code/flask-smorest
Author: Jérôme Lafréchoux
Author-email: jerome@jolimont.fr
License: MIT
Keywords: REST,openapi,swagger,flask,marshmallow,apispec,webargs
Platform: UNKNOWN
Classifier: Development Status :: 4 - Beta
Classifier: Intended Audience :: Developers
Classifier: Topic :: Internet :: WWW/HTTP
Classifier: Environment :: Web Environment
Classifier: Framework :: Flask
Classifier: License :: OSI Approved :: MIT License
Classifier: Programming Language :: Python :: 3.8
Classifier: Programming Language :: Python :: 3.9
Classifier: Programming Language :: Python :: 3.10
Classifier: Programming Language :: Python :: 3.11
Classifier: Programming Language :: Python :: 3.12
Classifier: Programming Language :: Python :: 3 :: Only
Requires-Python: >=3.8
Provides-Extra: dev
Provides-Extra: lint
Provides-Extra: tests
License-File: LICENSE
License-File: AUTHORS.rst
